cli/__init__.py
cli/runner.py
core/FileHandler.py
core/__init__.py
core/preprocessing.py
number_writer/__init__.py
number_writer/__main__.py
rules/LanguageRules.py
rules/PTRules.py
rules/__init__.py
tests/__init__.py
tests/test_file_reader.py
tests/test_separator.py
tests/test_writer.py
number_writer-0.0.2.dist-info/METADATA
number_writer-0.0.2.dist-info/WHEEL
number_writer-0.0.2.dist-info/top_level.txt
number_writer-0.0.2.dist-info/RECORD
