Metadata-Version: 2.1
Name: number-writer
Version: 0.0.2
Summary: A small package to transform number into text
Home-page: https://github.com/BrenoOsvaldoFunicheli/number_writer
Author: Breno Osvaldo
Author-email: bfunicheli@estudante.ufscar.com
License: UNKNOWN
Platform: UNKNOWN
Classifier: Programming Language :: Python :: 3
Classifier: License :: OSI Approved :: MIT License
